lamindb_schema/__init__.py
lamindb_schema-0.3.1.dist-info/LICENSE
lamindb_schema-0.3.1.dist-info/WHEEL
lamindb_schema-0.3.1.dist-info/METADATA
lamindb_schema-0.3.1.dist-info/RECORD
