Metadata-Version: 2.1
Name: lamindb_schema
Version: 0.3.1
Summary: Schema modules.
Author-email: Lamin Labs <laminlabs@gmail.com>
Requires-Dist: nbproject
Requires-Dist: lndb_schema_core
Requires-Dist: lndb_schema_bionty
Requires-Dist: lndb_schema_wetlab
Requires-Dist: pre-commit ; extra == "dev"
Requires-Dist: nox ; extra == "dev"
Requires-Dist: pytest>=6.0 ; extra == "test"
Requires-Dist: pytest-cov ; extra == "test"
Project-URL: Home, https://github.com/laminlabs/lamindb-schema
Provides-Extra: dev
Provides-Extra: test
